comptg2/__init__.py
comptg2/compare.py
comptg2/entry.py
comptg2/plot.py
comptg2-0.2.0.dist-info/LICENSE
comptg2-0.2.0.dist-info/METADATA
comptg2-0.2.0.dist-info/WHEEL
comptg2-0.2.0.dist-info/entry_points.txt
comptg2-0.2.0.dist-info/RECORD
