Metadata-Version: 2.1
Name: comptg2
Version: 0.2.0
Summary: Telomeric allele scoring tool for output from Telogator2.
License: GPL-3.0
Author: David Lougheed
Author-email: david.lougheed@mail.mcgill.ca
Requires-Python: >=3.10,<4.0
Classifier: License :: OSI Approved :: GNU General Public License v3 (GPLv3)
Classifier: Programming Language :: Python :: 3
Classifier: Programming Language :: Python :: 3.10
Classifier: Programming Language :: Python :: 3.11
Classifier: Programming Language :: Python :: 3.12
Requires-Dist: matplotlib (>=3.9.2,<4.0.0)
Requires-Dist: numpy (>=2.1.2,<3.0.0)
Requires-Dist: parasail (>=1.3.4,<2.0.0)
